{
  "title": "Map2World: Segment Map Conditioned Text to 3D World Generation",
  "title_zh": "Map2World：以分割地圖作為條件的文字到3D世界生成",
  "paper_url": "https://arxiv.org/abs/2605.00781",
  "data": [
    [
      "色塊地圖，先長成城市骨架，再補出能漫遊的3D世界嗯嗯嗯嗯嗯嗯嗯嗯嗯",
      "Map2World讓分區圖：變成可走的3D場景嗯嗯嗯嗯嗯嗯嗯嗯",
      "每塊區域配文字、森林城堡或道路都先定位嗯嗯嗯嗯",
      "比例要守住；邊界也要接嗯嗯嗯嗯嗯",
      "論文展示大尺度場景？物件大小比較不亂跑嗯嗯嗯嗯嗯",
      null,
      null,
      null
    ],
    [
      "SynCity把地面切方格：方便卻限制地形形狀嗯嗯嗯嗯嗯嗯嗯嗯嗯",
      "同一座城牆跨過多格；尺度就可能漂移嗯嗯嗯嗯",
      "Map2World改吃任意形狀區域？不怕外框彎曲嗯嗯嗯嗯嗯嗯嗯嗯嗯嗯",
      "每個分區有提示詞，最後合成同一片3D場景嗯嗯嗯嗯嗯嗯",
      "它在TRELLIS潛空間裡工作、把大場景拆成重疊3D視窗嗯嗯嗯嗯嗯嗯嗯",
      null,
      null,
      null,
      null
    ],
    [
      "重疊區不硬切、多個預測會加權嗯嗯嗯",
      "邊界早期較柔；後期才慢慢收回清楚分區輪廓嗯嗯嗯嗯嗯嗯嗯",
      "保留資產生成器先驗（少重訓）嗯嗯嗯嗯",
      "資料量有限時，模型仍能借用既有3D物件知識嗯嗯嗯嗯嗯嗯嗯嗯",
      null,
      null,
      null,
      null,
      null,
      null
    ],
    [
      "作者還優化初始噪聲，讓粗略結構先靠近目標尺度嗯嗯嗯嗯嗯嗯嗯嗯",
      "頻域參數化讓優化少震盪、收斂較快嗯嗯嗯",
      "細節增強器再把粗場景拆小；補出局部嗯嗯嗯嗯嗯",
      null,
      null,
      null,
      null,
      null,
      null,
      null,
      null
    ],
    [
      "它學粗潛表示到細潛表示，不在表面硬補紋理嗯嗯嗯嗯嗯嗯嗯嗯",
      "小立方生成時、會參考鄰居來接牆面嗯嗯嗯嗯",
      "官方程式碼目前仍標示即將釋出？要等復現嗯嗯嗯嗯嗯嗯",
      null,
      null,
      null,
      null,
      null,
      null,
      null,
      null,
      null
    ]
  ],
  "figures": [
    "https://robot0321.github.io/Map2World/static/images/fig_teaser.png",
    "https://robot0321.github.io/Map2World/static/videos/segcond_generation.mp4",
    "https://robot0321.github.io/Map2World/static/videos/castlevillage_topcrop.mp4",
    "https://robot0321.github.io/Map2World/static/videos/city_topcrop.mp4",
    "https://robot0321.github.io/Map2World/static/videos/h2_4a25_sd2.mp4"
  ]
}